slidgram/__init__.py
slidgram/__main__.py
slidgram/avatar.py
slidgram/command.py
slidgram/config.py
slidgram/contact.py
slidgram/errors.py
slidgram/gateway.py
slidgram/group.py
slidgram/reactions.py
slidgram/session.py
slidgram/telegram.py
slidgram/text_entities.py
slidgram/tg_msg.py
slidgram-0.3.0.dist-info/licenses/LICENSE
slidgram-0.3.0.dist-info/METADATA
slidgram-0.3.0.dist-info/WHEEL
slidgram-0.3.0.dist-info/entry_points.txt
slidgram-0.3.0.dist-info/top_level.txt
slidgram-0.3.0.dist-info/RECORD
