Metadata-Version: 2.4
Name: slidgram
Version: 0.3.0
Summary: A Telegram/XMPP gateway
Author-email: Nicolas Cedilnik <nicoco@nicoco.fr>
License-Expression: AGPL-3.0-or-later
Project-URL: Homepage, https://codeberg.org/slidge/slidgram
Project-URL: Issues, https://codeberg.org/slidge/slidgram/issues
Project-URL: Repository, https://codeberg.org/slidge/slidgram
Project-URL: Chat room, https://slidge.im/xmpp-web/#/guest?join=slidge@conference.nicoco.fr
Project-URL: Documentation, https://slidge.im/docs/slidgram/main
Project-URL: changelog, https://codeberg.org/slidge/slidgram/releases
Keywords: xmpp,gateway,bridge,instant messaging,chat,telegram
Classifier: Topic :: Internet :: XMPP
Requires-Python: >=3.11
License-File: LICENSE
Requires-Dist: pyrofork[speedup]<2.4,>=2.3.55
Requires-Dist: slidge<0.4,>=0.3.0alpha3
Requires-Dist: slidge-style-parser>=0.1.8
Dynamic: license-file
